MANIFEST.in
setup.py
hhic/__init__.py
hhic/connector.py
hhic/hh.py
hhic/tools.py
hhic.egg-info/PKG-INFO
hhic.egg-info/SOURCES.txt
hhic.egg-info/dependency_links.txt
hhic.egg-info/not-zip-safe
hhic.egg-info/requires.txt
hhic.egg-info/top_level.txt
hhic/connection/ca.key
hhic/connection/ca.pem
hhic/connection/ca.srl
hhic/connection/client.csr
hhic/connection/client.key
hhic/connection/client.pem
hhic/connection/server.csr
hhic/connection/server.key
hhic/connection/server.pem
hhic/demo/log1.txt
hhic/demo/log2.txt
hhic/demo/log3.txt