Metadata-Version: 1.0
Name: hhic
Version: 1.0
Summary: (homomorphic hash integrity checker) integrity checker for homomorphic ciphers with homomorphic hashes
Home-page: UNKNOWN
Author: Samim Faiz
Author-email: mhsamim.faiz@gmail.com
License: UNKNOWN
Platform: UNKNOWN
